prometheus_http_sd/__init__.py
prometheus_http_sd/app.py
prometheus_http_sd/cli.py
prometheus_http_sd/config.py
prometheus_http_sd/const.py
prometheus_http_sd/decorator.py
prometheus_http_sd/dispather.py
prometheus_http_sd/exceptions.py
prometheus_http_sd/mem_perf.py
prometheus_http_sd/metrics.py
prometheus_http_sd/redis/__init__.py
prometheus_http_sd/redis/cache.py
prometheus_http_sd/redis/queue.py
prometheus_http_sd/redis/server.py
prometheus_http_sd/redis/worker.py
prometheus_http_sd/sd.py
prometheus_http_sd/targets.py
prometheus_http_sd/templates/admin.html
prometheus_http_sd/validate.py
prometheus_http_sd/version.py
prometheus_http_sd-3.0.6.dist-info/METADATA
prometheus_http_sd-3.0.6.dist-info/WHEEL
prometheus_http_sd-3.0.6.dist-info/entry_points.txt
prometheus_http_sd-3.0.6.dist-info/licenses/LICENSE
prometheus_http_sd-3.0.6.dist-info/RECORD
