Metadata-Version: 2.4
Name: prometheus-http-sd
Version: 3.0.6
Summary: Prometheus HTTP SD framework.
License-File: LICENSE
Author: laixintao
Author-email: laixintaoo@gmail.com
Requires-Python: >=3.8,<4.0
Classifier: Programming Language :: Python :: 3
Classifier: Programming Language :: Python :: 3.8
Classifier: Programming Language :: Python :: 3.9
Classifier: Programming Language :: Python :: 3.10
Classifier: Programming Language :: Python :: 3.11
Classifier: Programming Language :: Python :: 3.12
Classifier: Programming Language :: Python :: 3.13
Classifier: Programming Language :: Python :: 3.14
Requires-Dist: Flask (>=2.1.3,<3.0.0)
Requires-Dist: PyYAML (>=6.0,<7.0)
Requires-Dist: prometheus-client (>=0.14.1,<0.15.0)
Requires-Dist: redis (>=4.5.0,<5.0.0)
Requires-Dist: sentry-sdk[flask] (==0.10.2)
Requires-Dist: waitress (>=2.1.2,<3.0.0)
Project-URL: Homepage, https://python-poetry.org://github.com/laixintao/prometheus-http-sd
